README.txt
plonetheme.GreenEarthTheme3_0-configure.zcml
setup.py
docs/HISTORY.txt
docs/INSTALL.txt
docs/LICENSE.GPL
docs/LICENSE.txt
plonetheme/__init__.py
plonetheme.GreenEarthTheme3_0.egg-info/PKG-INFO
plonetheme.GreenEarthTheme3_0.egg-info/SOURCES.txt
plonetheme.GreenEarthTheme3_0.egg-info/dependency_links.txt
plonetheme.GreenEarthTheme3_0.egg-info/entry_points.txt
plonetheme.GreenEarthTheme3_0.egg-info/namespace_packages.txt
plonetheme.GreenEarthTheme3_0.egg-info/not-zip-safe
plonetheme.GreenEarthTheme3_0.egg-info/paster_plugins.txt
plonetheme.GreenEarthTheme3_0.egg-info/requires.txt
plonetheme.GreenEarthTheme3_0.egg-info/top_level.txt
plonetheme/GreenEarthTheme3_0/__init__.py
plonetheme/GreenEarthTheme3_0/configure.zcml
plonetheme/GreenEarthTheme3_0/profiles.zcml
plonetheme/GreenEarthTheme3_0/setuphandlers.py
plonetheme/GreenEarthTheme3_0/skins.zcml
plonetheme/GreenEarthTheme3_0/tests.py
plonetheme/GreenEarthTheme3_0/version.txt
plonetheme/GreenEarthTheme3_0/browser/README.txt
plonetheme/GreenEarthTheme3_0/browser/__init__.py
plonetheme/GreenEarthTheme3_0/browser/configure.zcml
plonetheme/GreenEarthTheme3_0/browser/greenearth_footer.pt
plonetheme/GreenEarthTheme3_0/browser/greenearth_path_bar.pt
plonetheme/GreenEarthTheme3_0/browser/greenearth_personal_bar.pt
plonetheme/GreenEarthTheme3_0/browser/interfaces.py
plonetheme/GreenEarthTheme3_0/browser/viewlet.pt
plonetheme/GreenEarthTheme3_0/browser/viewlets.py
plonetheme/GreenEarthTheme3_0/profiles/default/cssregistry.xml
plonetheme/GreenEarthTheme3_0/profiles/default/import_steps.xml
plonetheme/GreenEarthTheme3_0/profiles/default/jsregistry.xml
plonetheme/GreenEarthTheme3_0/profiles/default/plonetheme.GreenEarthTheme3_0_various.txt
plonetheme/GreenEarthTheme3_0/profiles/default/skins.xml
plonetheme/GreenEarthTheme3_0/profiles/default/viewlets.xml
plonetheme/GreenEarthTheme3_0/skins/GreenEarthTheme3_0_images/header.jpg
plonetheme/GreenEarthTheme3_0/skins/GreenEarthTheme3_0_images/logo.gif
plonetheme/GreenEarthTheme3_0/skins/GreenEarthTheme3_0_styles/base_properties.props
plonetheme/GreenEarthTheme3_0/skins/GreenEarthTheme3_0_styles/greenearththeme3_0.css.dtml